qr_builder/__init__.py
qr_builder/api.py
qr_builder/auth.py
qr_builder/cli.py
qr_builder/config.py
qr_builder/core.py
qr_builder/utils.py
qr_builder-0.3.1.dist-info/licenses/LICENSE
qr_builder-0.3.1.dist-info/METADATA
qr_builder-0.3.1.dist-info/WHEEL
qr_builder-0.3.1.dist-info/entry_points.txt
qr_builder-0.3.1.dist-info/top_level.txt
qr_builder-0.3.1.dist-info/RECORD
