Metadata-Version: 2.4
Name: qr-builder
Version: 0.3.1
Summary: Generate and embed QR codes into images via Python, CLI, and FastAPI.
Author-email: AIQSO <dev@aiqso.io>
License: MIT
Project-URL: Homepage, https://github.com/qvidal01/qrcode
Project-URL: Source, https://github.com/qvidal01/qrcode
Project-URL: Issues, https://github.com/qvidal01/qrcode/issues
Project-URL: Documentation, https://github.com/qvidal01/qrcode#readme
Keywords: qr,qrcode,image,fastapi,cli,branding,marketing
Classifier: Programming Language :: Python :: 3
Classifier: Programming Language :: Python :: 3.10
Classifier: Programming Language :: Python :: 3.11
Classifier: Programming Language :: Python :: 3.12
Classifier: License :: OSI Approved :: MIT License
Classifier: Programming Language :: Python :: 3 :: Only
Classifier: Intended Audience :: Developers
Classifier: Topic :: Multimedia :: Graphics
Classifier: Framework :: FastAPI
Requires-Python: >=3.10
License-File: LICENSE
Requires-Dist: qrcode[pil]>=7.4.2
Requires-Dist: Pillow>=10.0.0
Requires-Dist: fastapi>=0.115.0
Requires-Dist: uvicorn[standard]>=0.30.0
Requires-Dist: python-multipart>=0.0.9
Requires-Dist: httpx>=0.27.0
Requires-Dist: amzqr>=0.0.1
Requires-Dist: pyqart>=0.1.0
Requires-Dist: segno>=1.6.0
Requires-Dist: qrcode-artistic>=3.0.0
Provides-Extra: dev
Requires-Dist: pytest>=8.0.0; extra == "dev"
Requires-Dist: pytest-cov>=4.0.0; extra == "dev"
Requires-Dist: httpx>=0.27.0; extra == "dev"
Requires-Dist: ruff>=0.4.0; extra == "dev"
Requires-Dist: mypy>=1.10.0; extra == "dev"
Dynamic: license-file
